telerivet/__init__.py
telerivet/airtimetransaction.py
telerivet/apicursor.py
telerivet/broadcast.py
telerivet/contact.py
telerivet/contactservicestate.py
telerivet/datarow.py
telerivet/datatable.py
telerivet/entity.py
telerivet/group.py
telerivet/label.py
telerivet/message.py
telerivet/organization.py
telerivet/phone.py
telerivet/project.py
telerivet/relativescheduledmessage.py
telerivet/route.py
telerivet/scheduledmessage.py
telerivet/service.py
telerivet/task.py
telerivet-1.7.0.dist-info/LICENSE
telerivet-1.7.0.dist-info/METADATA
telerivet-1.7.0.dist-info/WHEEL
telerivet-1.7.0.dist-info/top_level.txt
telerivet-1.7.0.dist-info/RECORD
