Metadata-Version: 2.1
Name: telerivet
Version: 1.7.0
Summary: Python client library for Telerivet REST API
Home-page: http://telerivet.com/
Author: Telerivet, Inc.
Author-email: support@telerivet.com
License: UNKNOWN
Platform: UNKNOWN
Classifier: Programming Language :: Python :: 2
Classifier: Programming Language :: Python :: 3
Classifier: License :: OSI Approved :: MIT License
Classifier: Operating System :: OS Independent
Requires-Python: >=2.6
Requires-Dist: requests (>=2.4.0)
